{
    "algorithm": "steffen_method", 
    "computation_time": 29.6861, 
    "instance": "pessimistic__mp_acp__30_6__3", 
    "local_search": true, 
    "objective_value": 1134.0, 
    "pax_order": [
        173, 
        42, 
        76, 
        75, 
        30, 
        163, 
        179, 
        176, 
        140, 
        121, 
        141, 
        128, 
        174, 
        93, 
        35, 
        136, 
        18, 
        155, 
        72, 
        12, 
        177, 
        81, 
        11, 
        23, 
        178, 
        111, 
        165, 
        150, 
        54, 
        3, 
        118, 
        56, 
        28, 
        109, 
        149, 
        53, 
        29, 
        37, 
        112, 
        46, 
        15, 
        85, 
        86, 
        0, 
        92, 
        122, 
        119, 
        97, 
        45, 
        98, 
        87, 
        99, 
        103, 
        130, 
        69, 
        134, 
        170, 
        148, 
        133, 
        32, 
        116, 
        4, 
        41, 
        145, 
        31, 
        172, 
        171, 
        52, 
        70, 
        127, 
        55, 
        43, 
        146, 
        169, 
        17, 
        66, 
        137, 
        90, 
        88, 
        168, 
        104, 
        94, 
        58, 
        26, 
        158, 
        60, 
        83, 
        123, 
        161, 
        22, 
        167, 
        49, 
        79, 
        138, 
        64, 
        153, 
        71, 
        20, 
        63, 
        59, 
        102, 
        16, 
        77, 
        108, 
        8, 
        48, 
        106, 
        25, 
        47, 
        27, 
        159, 
        14, 
        95, 
        117, 
        24, 
        164, 
        68, 
        101, 
        1, 
        113, 
        115, 
        62, 
        89, 
        91, 
        6, 
        160, 
        34, 
        9, 
        5, 
        175, 
        78, 
        19, 
        162, 
        120, 
        2, 
        38, 
        39, 
        166, 
        74, 
        124, 
        10, 
        80, 
        152, 
        154, 
        67, 
        110, 
        132, 
        13, 
        144, 
        126, 
        33, 
        40, 
        65, 
        114, 
        107, 
        44, 
        147, 
        143, 
        100, 
        129, 
        142, 
        36, 
        139, 
        82, 
        61, 
        135, 
        156, 
        105, 
        51, 
        84, 
        151, 
        96, 
        7, 
        131, 
        157, 
        21, 
        73, 
        50, 
        125, 
        57
    ], 
    "with_groups": false, 
    "with_seat_interference": false
}