{
    "algorithm": "max_clear_row", 
    "computation_time": 0.038, 
    "instance": "mp_acp__20_2__9", 
    "local_search": true, 
    "objective_value": 193.7, 
    "pax_order": [
        1, 
        23, 
        39, 
        2, 
        32, 
        25, 
        36, 
        38, 
        28, 
        10, 
        16, 
        12, 
        6, 
        17, 
        11, 
        27, 
        8, 
        20, 
        3, 
        4, 
        21, 
        26, 
        35, 
        9, 
        30, 
        15, 
        5, 
        33, 
        0, 
        24, 
        29, 
        37, 
        22, 
        19, 
        7, 
        18, 
        13, 
        31, 
        14, 
        34
    ], 
    "with_groups": false, 
    "with_seat_interference": false
}