{
    "algorithm": "mip_predecessor_assignment", 
    "computation_time": 7200.0859, 
    "dual_bound": 147.1, 
    "instance": "mp_acp__20_2__2", 
    "objective_value": 207.8, 
    "pax_order": [
        16, 
        12, 
        4, 
        22, 
        1, 
        14, 
        32, 
        36, 
        33, 
        15, 
        11, 
        9, 
        26, 
        5, 
        8, 
        13, 
        29, 
        0, 
        19, 
        3, 
        23, 
        21, 
        31, 
        27, 
        2, 
        10, 
        20, 
        18, 
        38, 
        24, 
        7, 
        25, 
        6, 
        30, 
        17, 
        34, 
        37, 
        35, 
        28, 
        39
    ], 
    "time_limit": 7200, 
    "with_groups": true, 
    "with_seat_interference": false
}