{
    "algorithm": "steffen_method", 
    "computation_time": 5.3301, 
    "instance": "mp_ac__20_6__0", 
    "local_search": true, 
    "objective_value": 645.4, 
    "pax_order": [
        6, 
        25, 
        70, 
        91, 
        115, 
        36, 
        88, 
        73, 
        29, 
        86, 
        116, 
        33, 
        64, 
        85, 
        11, 
        26, 
        52, 
        84, 
        24, 
        43, 
        3, 
        30, 
        32, 
        71, 
        15, 
        92, 
        8, 
        100, 
        101, 
        68, 
        113, 
        31, 
        78, 
        89, 
        117, 
        34, 
        79, 
        45, 
        57, 
        95, 
        72, 
        108, 
        107, 
        48, 
        17, 
        22, 
        46, 
        10, 
        41, 
        21, 
        56, 
        50, 
        83, 
        90, 
        28, 
        81, 
        82, 
        97, 
        94, 
        105, 
        38, 
        93, 
        53, 
        106, 
        62, 
        44, 
        1, 
        39, 
        60, 
        9, 
        12, 
        76, 
        23, 
        5, 
        20, 
        42, 
        4, 
        2, 
        99, 
        103, 
        102, 
        47, 
        96, 
        35, 
        58, 
        77, 
        37, 
        49, 
        119, 
        16, 
        98, 
        104, 
        51, 
        14, 
        69, 
        112, 
        114, 
        118, 
        109, 
        19, 
        65, 
        55, 
        63, 
        0, 
        75, 
        27, 
        13, 
        66, 
        18, 
        61, 
        54, 
        67, 
        111, 
        7, 
        80, 
        87, 
        59, 
        74, 
        40, 
        110
    ], 
    "with_groups": false, 
    "with_seat_interference": false
}