{
    "algorithm": "random_shuffle", 
    "computation_time": 0.1503, 
    "instance": "mp_ac__30_2__2", 
    "max_iterations": 1000, 
    "objective_value": 220.8, 
    "pax_order": [
        11, 
        21, 
        53, 
        22, 
        26, 
        46, 
        4, 
        7, 
        45, 
        34, 
        14, 
        23, 
        44, 
        13, 
        24, 
        25, 
        17, 
        36, 
        54, 
        16, 
        32, 
        27, 
        56, 
        28, 
        10, 
        12, 
        5, 
        6, 
        0, 
        35, 
        1, 
        15, 
        42, 
        57, 
        47, 
        29, 
        58, 
        18, 
        55, 
        9, 
        43, 
        52, 
        8, 
        19, 
        50, 
        48, 
        39, 
        38, 
        2, 
        20, 
        59, 
        31, 
        33, 
        3, 
        41, 
        40, 
        30, 
        49, 
        51, 
        37
    ], 
    "solution_values": [
        272.3, 
        263.2, 
        265.3, 
        243.8, 
        257.6, 
        256.5, 
        247.0, 
        245.6, 
        249.8, 
        260.3, 
        240.0, 
        269.7, 
        244.6, 
        266.6, 
        259.4, 
        259.2, 
        270.5, 
        252.9, 
        273.5, 
        258.9, 
        237.3, 
        256.6, 
        250.3, 
        250.4, 
        253.8, 
        251.2, 
        269.1, 
        263.6, 
        249.3, 
        256.7, 
        278.8, 
        264.8, 
        251.5, 
        251.0, 
        263.5, 
        245.6, 
        277.2, 
        258.2, 
        258.1, 
        279.5, 
        271.6, 
        265.9, 
        259.1, 
        256.4, 
        257.4, 
        269.5, 
        264.8, 
        265.4, 
        262.2, 
        268.6, 
        271.5, 
        263.9, 
        270.0, 
        260.0, 
        265.7, 
        272.8, 
        261.8, 
        261.9, 
        243.5, 
        278.0, 
        253.6, 
        258.6, 
        254.1, 
        250.3, 
        281.2, 
        250.2, 
        265.6, 
        259.7, 
        253.6, 
        254.0, 
        271.8, 
        252.9, 
        238.8, 
        253.4, 
        268.6, 
        258.9, 
        258.2, 
        267.0, 
        272.1, 
        271.5, 
        268.3, 
        274.2, 
        247.5, 
        244.6, 
        236.4, 
        267.6, 
        277.9, 
        258.0, 
        254.4, 
        250.2, 
        264.3, 
        265.0, 
        257.2, 
        259.7, 
        241.2, 
        265.3, 
        261.6, 
        279.4, 
        232.5, 
        256.0, 
        263.7, 
        251.8, 
        252.4, 
        265.6, 
        265.5, 
        259.7, 
        263.7, 
        257.8, 
        275.0, 
        266.3, 
        268.0, 
        249.3, 
        258.7, 
        270.2, 
        274.5, 
        259.9, 
        254.3, 
        278.6, 
        242.7, 
        262.3, 
        273.8, 
        258.4, 
        268.9, 
        261.7, 
        264.4, 
        272.5, 
        269.2, 
        277.5, 
        277.6, 
        264.0, 
        273.6, 
        255.7, 
        257.5, 
        244.7, 
        248.0, 
        256.5, 
        246.3, 
        247.9, 
        257.0, 
        255.2, 
        273.4, 
        265.3, 
        268.8, 
        262.7, 
        262.4, 
        254.7, 
        268.4, 
        277.2, 
        272.7, 
        258.7, 
        285.3, 
        250.7, 
        258.8, 
        265.2, 
        268.3, 
        240.5, 
        261.3, 
        272.5, 
        255.7, 
        270.9, 
        266.2, 
        269.6, 
        251.4, 
        264.3, 
        243.7, 
        263.8, 
        268.2, 
        272.6, 
        269.5, 
        274.2, 
        258.6, 
        262.6, 
        271.3, 
        277.4, 
        270.1, 
        260.0, 
        270.4, 
        271.1, 
        269.8, 
        275.0, 
        257.1, 
        276.0, 
        264.8, 
        237.0, 
        273.2, 
        245.7, 
        254.7, 
        261.3, 
        273.6, 
        257.0, 
        258.4, 
        269.2, 
        250.0, 
        286.0, 
        263.2, 
        261.0, 
        268.3, 
        268.2, 
        254.1, 
        264.3, 
        263.2, 
        288.0, 
        258.4, 
        272.2, 
        260.6, 
        265.6, 
        260.6, 
        270.0, 
        240.9, 
        270.6, 
        245.6, 
        267.2, 
        248.6, 
        257.4, 
        256.2, 
        270.8, 
        247.4, 
        262.3, 
        265.4, 
        265.1, 
        254.8, 
        273.9, 
        248.5, 
        250.1, 
        272.4, 
        229.8, 
        253.5, 
        258.2, 
        268.8, 
        246.7, 
        259.1, 
        265.8, 
        267.0, 
        271.4, 
        273.0, 
        272.2, 
        244.1, 
        287.6, 
        257.1, 
        271.0, 
        255.8, 
        252.2, 
        249.6, 
        266.5, 
        275.8, 
        267.2, 
        282.9, 
        277.9, 
        262.1, 
        249.8, 
        246.5, 
        265.1, 
        281.8, 
        276.5, 
        269.8, 
        256.4, 
        267.3, 
        278.5, 
        263.6, 
        263.9, 
        272.0, 
        263.7, 
        263.9, 
        270.5, 
        271.0, 
        249.0, 
        245.2, 
        265.6, 
        266.1, 
        250.4, 
        249.4, 
        259.5, 
        264.0, 
        261.4, 
        279.0, 
        263.0, 
        274.9, 
        258.4, 
        263.4, 
        258.5, 
        275.4, 
        271.0, 
        258.1, 
        254.1, 
        266.2, 
        258.7, 
        261.7, 
        260.8, 
        265.3, 
        262.8, 
        254.0, 
        267.3, 
        240.0, 
        253.6, 
        267.0, 
        273.3, 
        262.2, 
        274.9, 
        272.1, 
        266.9, 
        244.5, 
        282.7, 
        272.3, 
        255.1, 
        276.6, 
        259.4, 
        256.5, 
        259.2, 
        263.2, 
        266.6, 
        247.6, 
        242.4, 
        259.4, 
        249.1, 
        276.3, 
        277.1, 
        229.1, 
        267.5, 
        255.9, 
        251.2, 
        274.1, 
        269.6, 
        257.0, 
        259.8, 
        271.8, 
        271.8, 
        250.2, 
        251.5, 
        265.5, 
        271.6, 
        248.0, 
        266.7, 
        262.2, 
        250.7, 
        255.7, 
        253.8, 
        252.2, 
        263.3, 
        258.0, 
        271.4, 
        267.6, 
        253.1, 
        277.5, 
        251.2, 
        255.5, 
        243.3, 
        253.7, 
        248.9, 
        256.9, 
        243.9, 
        244.9, 
        263.6, 
        249.9, 
        261.6, 
        265.7, 
        257.7, 
        269.9, 
        254.8, 
        286.5, 
        255.9, 
        258.3, 
        254.9, 
        266.0, 
        261.5, 
        257.9, 
        255.6, 
        241.2, 
        265.3, 
        259.5, 
        262.8, 
        283.2, 
        251.3, 
        253.6, 
        267.9, 
        281.7, 
        265.4, 
        271.1, 
        249.4, 
        240.8, 
        265.9, 
        270.3, 
        281.0, 
        257.7, 
        245.6, 
        257.6, 
        272.3, 
        263.3, 
        264.3, 
        269.3, 
        274.3, 
        255.5, 
        253.3, 
        273.1, 
        251.5, 
        276.7, 
        266.4, 
        252.4, 
        258.9, 
        260.4, 
        276.7, 
        266.1, 
        264.8, 
        246.4, 
        258.9, 
        254.2, 
        273.2, 
        253.3, 
        259.1, 
        248.3, 
        270.7, 
        244.7, 
        250.0, 
        271.2, 
        279.7, 
        259.3, 
        271.1, 
        256.8, 
        268.5, 
        259.8, 
        249.0, 
        272.2, 
        246.0, 
        286.2, 
        247.0, 
        271.3, 
        261.9, 
        256.4, 
        265.0, 
        241.7, 
        249.5, 
        268.8, 
        260.6, 
        260.1, 
        271.6, 
        256.4, 
        281.0, 
        279.6, 
        258.8, 
        261.9, 
        255.0, 
        267.3, 
        268.4, 
        253.4, 
        251.1, 
        258.3, 
        240.6, 
        263.7, 
        265.7, 
        267.1, 
        272.9, 
        261.2, 
        251.5, 
        269.6, 
        247.9, 
        255.4, 
        270.5, 
        237.9, 
        269.6, 
        270.0, 
        267.6, 
        276.9, 
        266.3, 
        250.9, 
        259.8, 
        267.5, 
        262.0, 
        270.1, 
        262.9, 
        260.0, 
        264.3, 
        260.7, 
        278.3, 
        269.4, 
        267.2, 
        255.9, 
        248.1, 
        265.9, 
        249.5, 
        266.9, 
        260.3, 
        260.7, 
        253.2, 
        261.3, 
        263.3, 
        261.8, 
        255.6, 
        262.9, 
        256.9, 
        253.1, 
        257.2, 
        248.5, 
        243.2, 
        247.1, 
        268.2, 
        259.4, 
        265.0, 
        274.5, 
        245.0, 
        259.4, 
        252.8, 
        244.6, 
        270.5, 
        273.8, 
        271.0, 
        244.8, 
        262.1, 
        269.4, 
        264.2, 
        265.6, 
        276.1, 
        248.5, 
        262.6, 
        267.2, 
        239.2, 
        273.6, 
        277.3, 
        250.8, 
        243.5, 
        275.3, 
        273.5, 
        254.1, 
        260.1, 
        256.7, 
        269.1, 
        254.4, 
        250.6, 
        251.0, 
        264.1, 
        260.9, 
        226.9, 
        283.3, 
        255.2, 
        258.8, 
        268.6, 
        260.5, 
        268.9, 
        260.1, 
        273.7, 
        267.3, 
        266.7, 
        267.3, 
        265.6, 
        287.0, 
        259.5, 
        279.6, 
        259.3, 
        277.2, 
        259.6, 
        265.1, 
        244.6, 
        231.8, 
        246.4, 
        264.6, 
        265.1, 
        269.4, 
        274.5, 
        252.0, 
        255.6, 
        266.5, 
        267.0, 
        272.6, 
        273.2, 
        266.5, 
        264.4, 
        228.4, 
        264.4, 
        256.0, 
        253.7, 
        275.1, 
        258.3, 
        251.3, 
        259.6, 
        273.3, 
        242.3, 
        262.5, 
        257.4, 
        268.5, 
        263.5, 
        265.3, 
        263.5, 
        277.6, 
        264.5, 
        251.3, 
        282.1, 
        257.9, 
        268.5, 
        262.5, 
        250.0, 
        272.2, 
        273.6, 
        257.0, 
        269.5, 
        260.6, 
        249.0, 
        255.5, 
        266.9, 
        254.0, 
        260.2, 
        262.9, 
        246.8, 
        261.5, 
        270.1, 
        266.3, 
        260.0, 
        261.6, 
        276.9, 
        280.1, 
        260.0, 
        274.0, 
        241.0, 
        243.8, 
        260.6, 
        242.5, 
        268.8, 
        270.4, 
        235.2, 
        257.2, 
        265.7, 
        238.6, 
        277.1, 
        248.3, 
        244.4, 
        255.2, 
        264.3, 
        261.4, 
        275.7, 
        242.8, 
        279.9, 
        248.7, 
        278.0, 
        248.2, 
        255.3, 
        258.1, 
        266.9, 
        238.8, 
        254.2, 
        262.2, 
        279.1, 
        281.5, 
        260.0, 
        265.9, 
        271.4, 
        253.7, 
        271.6, 
        262.4, 
        260.2, 
        250.5, 
        270.6, 
        269.2, 
        260.0, 
        269.0, 
        275.3, 
        257.8, 
        256.9, 
        237.0, 
        264.5, 
        240.5, 
        254.6, 
        255.9, 
        250.7, 
        251.4, 
        272.9, 
        260.5, 
        260.5, 
        248.4, 
        265.6, 
        275.0, 
        268.7, 
        258.7, 
        250.9, 
        272.7, 
        274.4, 
        255.3, 
        265.0, 
        279.2, 
        274.8, 
        257.3, 
        272.9, 
        268.6, 
        245.5, 
        255.6, 
        262.3, 
        248.4, 
        256.9, 
        264.8, 
        247.4, 
        236.4, 
        257.5, 
        231.7, 
        276.8, 
        257.8, 
        255.0, 
        248.2, 
        264.8, 
        255.9, 
        238.6, 
        268.8, 
        260.3, 
        238.1, 
        267.1, 
        260.0, 
        264.0, 
        247.7, 
        258.5, 
        251.4, 
        256.8, 
        273.9, 
        268.9, 
        265.6, 
        255.9, 
        267.6, 
        266.5, 
        245.7, 
        276.4, 
        255.7, 
        259.0, 
        272.9, 
        261.3, 
        272.5, 
        277.7, 
        275.0, 
        271.6, 
        261.8, 
        257.3, 
        256.8, 
        231.2, 
        256.7, 
        258.1, 
        275.8, 
        259.0, 
        265.1, 
        262.0, 
        252.6, 
        251.7, 
        267.0, 
        274.9, 
        267.4, 
        246.5, 
        255.5, 
        259.7, 
        266.1, 
        274.6, 
        276.6, 
        252.0, 
        262.6, 
        270.2, 
        259.7, 
        250.4, 
        268.8, 
        275.0, 
        274.2, 
        262.9, 
        254.5, 
        243.4, 
        268.4, 
        260.6, 
        269.9, 
        254.5, 
        255.9, 
        256.9, 
        266.1, 
        281.1, 
        264.3, 
        239.9, 
        251.3, 
        247.1, 
        251.9, 
        250.9, 
        271.3, 
        284.4, 
        259.0, 
        249.8, 
        259.6, 
        260.1, 
        267.8, 
        262.2, 
        263.7, 
        279.8, 
        242.5, 
        257.1, 
        256.2, 
        257.3, 
        246.6, 
        270.0, 
        245.2, 
        270.6, 
        263.1, 
        274.2, 
        273.8, 
        255.3, 
        258.9, 
        268.2, 
        267.3, 
        261.1, 
        272.0, 
        260.3, 
        261.2, 
        271.3, 
        274.1, 
        242.8, 
        252.2, 
        272.7, 
        259.3, 
        258.8, 
        251.1, 
        251.3, 
        254.7, 
        249.5, 
        262.5, 
        257.3, 
        265.5, 
        263.7, 
        276.8, 
        260.7, 
        257.2, 
        231.7, 
        276.3, 
        260.3, 
        272.8, 
        246.9, 
        267.3, 
        280.0, 
        249.5, 
        256.3, 
        260.3, 
        266.0, 
        256.0, 
        270.1, 
        251.9, 
        271.8, 
        241.9, 
        268.9, 
        271.8, 
        248.7, 
        255.8, 
        255.6, 
        248.7, 
        247.6, 
        263.9, 
        276.2, 
        258.2, 
        245.0, 
        264.6, 
        260.2, 
        260.9, 
        264.7, 
        248.7, 
        269.1, 
        267.7, 
        238.3, 
        265.5, 
        248.2, 
        230.5, 
        263.1, 
        220.8, 
        246.5, 
        275.3, 
        267.6, 
        256.9, 
        261.9, 
        247.9, 
        248.9, 
        258.7, 
        266.0, 
        272.3, 
        267.4, 
        268.6, 
        272.0, 
        249.0, 
        250.2, 
        269.3, 
        263.7, 
        261.6, 
        257.7, 
        262.7, 
        254.2, 
        262.6, 
        248.1, 
        258.3, 
        255.4, 
        267.5, 
        282.7, 
        259.1, 
        266.7, 
        246.2, 
        264.5, 
        253.9, 
        282.7, 
        256.8, 
        259.8, 
        267.7, 
        267.4, 
        253.9, 
        257.0, 
        245.1, 
        266.6, 
        271.1, 
        259.4, 
        234.7, 
        258.4, 
        271.2, 
        260.6, 
        252.7, 
        268.4, 
        255.4, 
        259.7, 
        259.8, 
        246.6, 
        264.6, 
        260.5, 
        273.0, 
        269.4, 
        260.5, 
        267.7, 
        258.5, 
        270.8, 
        269.7, 
        249.1, 
        271.3, 
        263.7, 
        253.1, 
        263.7, 
        244.9, 
        259.2, 
        262.3, 
        258.2, 
        266.4, 
        256.5, 
        249.6, 
        271.5, 
        250.9, 
        246.7, 
        278.6, 
        273.2, 
        260.2, 
        262.5, 
        272.0, 
        248.0, 
        246.5, 
        261.0, 
        236.9, 
        268.7, 
        277.1, 
        268.2, 
        249.2, 
        260.5, 
        247.6, 
        257.0, 
        274.4, 
        262.4, 
        263.8, 
        255.8, 
        260.8, 
        229.1, 
        265.1, 
        227.9, 
        263.1, 
        266.8, 
        277.4, 
        265.1, 
        260.9, 
        245.8, 
        254.9, 
        272.2, 
        269.6, 
        239.3, 
        258.0, 
        278.6, 
        250.7, 
        266.4, 
        247.3, 
        266.3, 
        271.1, 
        269.8, 
        264.4, 
        271.9, 
        256.5, 
        262.6, 
        276.9, 
        254.5, 
        246.3, 
        276.6, 
        268.2, 
        240.0, 
        255.3, 
        238.0, 
        252.6, 
        267.2, 
        277.2, 
        256.1, 
        260.5, 
        282.7, 
        261.2, 
        280.8, 
        273.8, 
        274.2, 
        253.4, 
        266.2, 
        259.8, 
        246.0
    ], 
    "with_groups": false, 
    "with_seat_interference": false
}