{
    "algorithm": "MinimumMaximumPax", 
    "computation_time": 0.5774, 
    "dual_bound": 81.1, 
    "instance": "mp_acp__10_2__9", 
    "objective_value": 81.1, 
    "pax_seats": [
        [
            4, 
            1
        ], 
        [
            7, 
            0
        ], 
        [
            6, 
            0
        ], 
        [
            3, 
            0
        ], 
        [
            6, 
            1
        ], 
        [
            0, 
            1
        ], 
        [
            5, 
            0
        ], 
        [
            9, 
            0
        ], 
        [
            1, 
            1
        ], 
        [
            8, 
            1
        ], 
        [
            0, 
            0
        ], 
        [
            5, 
            1
        ], 
        [
            7, 
            1
        ], 
        [
            4, 
            0
        ], 
        [
            9, 
            1
        ], 
        [
            1, 
            0
        ], 
        [
            3, 
            1
        ], 
        [
            2, 
            0
        ], 
        [
            2, 
            1
        ], 
        [
            8, 
            0
        ]
    ], 
    "with_seat_interference": false, 
    "with_seat_preference": false
}