{
    "algorithm": "outside_in_back_to_front", 
    "computation_time": 0.034, 
    "instance": "perturbed__mp_acp__10_4__7", 
    "local_search": true, 
    "objective_value": 301.3, 
    "pax_order": [
        17, 
        39, 
        14, 
        36, 
        31, 
        38, 
        21, 
        1, 
        12, 
        35, 
        4, 
        0, 
        27, 
        8, 
        30, 
        6, 
        7, 
        10, 
        26, 
        3, 
        29, 
        33, 
        24, 
        20, 
        16, 
        28, 
        23, 
        32, 
        13, 
        2, 
        9, 
        22, 
        15, 
        37, 
        18, 
        5, 
        25, 
        19, 
        11, 
        34
    ], 
    "with_groups": false, 
    "with_seat_interference": false
}