{
    "algorithm": "outside_in_back_to_front", 
    "computation_time": 1.1177, 
    "instance": "mp_acp__10_6__4", 
    "local_search": true, 
    "objective_value": 393.4, 
    "pax_order": [
        3, 
        6, 
        12, 
        50, 
        40, 
        5, 
        38, 
        35, 
        42, 
        31, 
        41, 
        51, 
        9, 
        32, 
        27, 
        17, 
        15, 
        54, 
        33, 
        34, 
        2, 
        19, 
        46, 
        21, 
        8, 
        47, 
        26, 
        0, 
        28, 
        44, 
        56, 
        7, 
        24, 
        49, 
        4, 
        16, 
        45, 
        39, 
        57, 
        59, 
        22, 
        25, 
        30, 
        53, 
        43, 
        23, 
        37, 
        20, 
        10, 
        48, 
        29, 
        1, 
        36, 
        11, 
        58, 
        13, 
        14, 
        52, 
        18, 
        55
    ], 
    "with_groups": false, 
    "with_seat_interference": true
}