{
    "algorithm": "steffen_method", 
    "computation_time": 2.7284, 
    "instance": "mp_acp__20_4__6", 
    "local_search": true, 
    "objective_value": 454.1, 
    "pax_order": [
        65, 
        60, 
        42, 
        6, 
        36, 
        23, 
        67, 
        45, 
        74, 
        25, 
        76, 
        47, 
        48, 
        9, 
        29, 
        73, 
        79, 
        46, 
        28, 
        51, 
        63, 
        0, 
        52, 
        8, 
        75, 
        43, 
        32, 
        3, 
        37, 
        17, 
        44, 
        38, 
        10, 
        54, 
        55, 
        19, 
        4, 
        21, 
        72, 
        71, 
        64, 
        5, 
        59, 
        34, 
        20, 
        1, 
        62, 
        68, 
        24, 
        56, 
        7, 
        26, 
        41, 
        33, 
        78, 
        18, 
        40, 
        22, 
        27, 
        58, 
        15, 
        13, 
        66, 
        77, 
        11, 
        53, 
        50, 
        30, 
        57, 
        61, 
        69, 
        12, 
        16, 
        2, 
        49, 
        35, 
        39, 
        31, 
        14, 
        70
    ], 
    "with_groups": true, 
    "with_seat_interference": true
}